deepagents/__init__.py
deepagents/graph.py
deepagents/backends/__init__.py
deepagents/backends/composite.py
deepagents/backends/filesystem.py
deepagents/backends/protocol.py
deepagents/backends/sandbox.py
deepagents/backends/state.py
deepagents/backends/store.py
deepagents/backends/utils.py
deepagents/middleware/__init__.py
deepagents/middleware/filesystem.py
deepagents/middleware/patch_tool_calls.py
deepagents/middleware/subagents.py
openmle_cli/__init__.py
openmle_cli/__main__.py
openmle_cli/agent.py
openmle_cli/agent_memory.py
openmle_cli/commands.py
openmle_cli/config.py
openmle_cli/default_agent_prompt.md
openmle_cli/execution.py
openmle_cli/file_ops.py
openmle_cli/input.py
openmle_cli/main.py
openmle_cli/project_utils.py
openmle_cli/py.typed
openmle_cli/shell.py
openmle_cli/token_utils.py
openmle_cli/tools.py
openmle_cli/ui.py
openmle_cli/builtin_skills/__init__.py
openmle_cli/builtin_skills/classical-ml/SKILL.md
openmle_cli/builtin_skills/data-engineering/SKILL.md
openmle_cli/builtin_skills/deep-learning/SKILL.md
openmle_cli/builtin_skills/evaluation/SKILL.md
openmle_cli/builtin_skills/infra-cost/SKILL.md
openmle_cli/builtin_skills/llm-agent/SKILL.md
openmle_cli/builtin_skills/ml-docs/SKILL.md
openmle_cli/builtin_skills/mlops-production/SKILL.md
openmle_cli/builtin_skills/problem-framing/SKILL.md
openmle_cli/builtin_skills/safety-governance/SKILL.md
openmle_cli/builtin_skills/web-research/SKILL.md
openmle_cli/integrations/__init__.py
openmle_cli/integrations/daytona.py
openmle_cli/integrations/modal.py
openmle_cli/integrations/runloop.py
openmle_cli/integrations/sandbox_factory.py
openmle_cli/skills/__init__.py
openmle_cli/skills/commands.py
openmle_cli/skills/load.py
openmle_cli/skills/middleware.py
open_mle-0.0.1.dist-info/METADATA
open_mle-0.0.1.dist-info/WHEEL
open_mle-0.0.1.dist-info/entry_points.txt
open_mle-0.0.1.dist-info/top_level.txt
open_mle-0.0.1.dist-info/RECORD
