Metadata-Version: 2.4
Name: open-mle
Version: 0.0.1
Summary: openMLE CLI
Author-email: Lalan Kumar <lalan.k.4590@gmail.com>
License: MIT
Project-URL: Homepage, https://github.com/kumar8074/open-mle
Project-URL: Repository, https://github.com/kumar8074/open-mle
Keywords: mle,cli,machine-learning
Classifier: Development Status :: 3 - Alpha
Classifier: Intended Audience :: Developers
Classifier: Programming Language :: Python :: 3.12
Classifier: Programming Language :: Python :: 3.13
Requires-Python: <4.0,>=3.12
Requires-Dist: daytona>=0.124.0
Requires-Dist: langchain>=1.1.3
Requires-Dist: langchain-anthropic>=1.2.0
Requires-Dist: langchain-google-genai>=4.0.0
Requires-Dist: langchain-openai>=1.1.2
Requires-Dist: langgraph>=1.0.4
Requires-Dist: markdownify>=1.2.2
Requires-Dist: modal>=1.2.4
Requires-Dist: prompt-toolkit>=3.0.52
Requires-Dist: python-dotenv>=1.2.1
Requires-Dist: requests>=2.32.5
Requires-Dist: rich>=14.2.0
Requires-Dist: runloop-api-client>=1.2.0
Requires-Dist: tavily-python>=0.7.14
Requires-Dist: wcmatch>=10.1
